pytest_tmp_files/__init__.py
pytest_tmp_files/make.py
pytest_tmp_files/plugin.py
pytest_tmp_files-0.0.1.dist-info/entry_points.txt
pytest_tmp_files-0.0.1.dist-info/LICENSE.txt
pytest_tmp_files-0.0.1.dist-info/WHEEL
pytest_tmp_files-0.0.1.dist-info/METADATA
pytest_tmp_files-0.0.1.dist-info/RECORD
