Metadata-Version: 2.1
Name: pytest_tmp_files
Version: 0.0.1
Summary: Utilities to create temporary file hierarchies in pytest.
Author-email: Kale Kundert <kale@thekunderts.net>
Requires-Python: ~=3.7
Classifier: Programming Language :: Python :: 3
Requires-Dist: pytest
Requires-Dist: python-dateutil
Requires-Dist: sphinx ; extra == "doc"
Requires-Dist: sphinx_rtd_theme ; extra == "doc"
Requires-Dist: autoclasstoc ; extra == "doc"
Requires-Dist: pytest ; extra == "test"
Requires-Dist: pytest-cov ; extra == "test"
Requires-Dist: coveralls ; extra == "test"
Project-URL: Bug Tracker, https://github.com/kalekundert/pytest_tmp_files/issues
Project-URL: Continuous Integration, https://github.com/kalekundert/pytest_tmp_files/actions
Project-URL: Documentation, https://pytest_tmp_files.readthedocs.io/en/latest/
Project-URL: Test Coverage, https://coveralls.io/github/kalekundert/pytest_tmp_files
Project-URL: Version Control, https://github.com/kalekundert/pytest_tmp_files
Provides-Extra: doc
Provides-Extra: test
